cdktf_cdktf_provider_github/__init__.py
cdktf_cdktf_provider_github/py.typed
cdktf_cdktf_provider_github/_jsii/__init__.py
cdktf_cdktf_provider_github/_jsii/provider-github@15.2.2.jsii.tgz
cdktf_cdktf_provider_github/actions_environment_secret/__init__.py
cdktf_cdktf_provider_github/actions_environment_variable/__init__.py
cdktf_cdktf_provider_github/actions_organization_oidc_subject_claim_customization_template/__init__.py
cdktf_cdktf_provider_github/actions_organization_permissions/__init__.py
cdktf_cdktf_provider_github/actions_organization_secret/__init__.py
cdktf_cdktf_provider_github/actions_organization_secret_repositories/__init__.py
cdktf_cdktf_provider_github/actions_organization_secret_repository/__init__.py
cdktf_cdktf_provider_github/actions_organization_variable/__init__.py
cdktf_cdktf_provider_github/actions_repository_access_level/__init__.py
cdktf_cdktf_provider_github/actions_repository_oidc_subject_claim_customization_template/__init__.py
cdktf_cdktf_provider_github/actions_repository_permissions/__init__.py
cdktf_cdktf_provider_github/actions_runner_group/__init__.py
cdktf_cdktf_provider_github/actions_secret/__init__.py
cdktf_cdktf_provider_github/actions_variable/__init__.py
cdktf_cdktf_provider_github/app_installation_repositories/__init__.py
cdktf_cdktf_provider_github/app_installation_repository/__init__.py
cdktf_cdktf_provider_github/branch/__init__.py
cdktf_cdktf_provider_github/branch_default/__init__.py
cdktf_cdktf_provider_github/branch_protection/__init__.py
cdktf_cdktf_provider_github/branch_protection_v3/__init__.py
cdktf_cdktf_provider_github/codespaces_organization_secret/__init__.py
cdktf_cdktf_provider_github/codespaces_organization_secret_repositories/__init__.py
cdktf_cdktf_provider_github/codespaces_secret/__init__.py
cdktf_cdktf_provider_github/codespaces_user_secret/__init__.py
cdktf_cdktf_provider_github/data_github_actions_environment_public_key/__init__.py
cdktf_cdktf_provider_github-15.2.2.dist-info/LICENSE
cdktf_cdktf_provider_github-15.2.2.dist-info/METADATA
cdktf_cdktf_provider_github-15.2.2.dist-info/WHEEL
cdktf_cdktf_provider_github-15.2.2.dist-info/top_level.txt
cdktf_cdktf_provider_github-15.2.2.dist-info/RECORD
